kdb.py
kraken_db_builder-0.1.3.dist-info/entry_points.txt
kraken_db_builder-0.1.3.dist-info/LICENSE.txt
kraken_db_builder-0.1.3.dist-info/WHEEL
kraken_db_builder-0.1.3.dist-info/METADATA
kraken_db_builder-0.1.3.dist-info/RECORD
