Metadata-Version: 2.1
Name: kraken-db-builder
Version: 0.1.3
Summary: CLI tool to build any kraken2 database with single command
Maintainer-email: ChillarAnand <chillar@avilpage.com>
Requires-Python: >=3.8
Classifier: Development Status :: 4 - Beta
Classifier: Intended Audience :: Developers
Classifier: License :: OSI Approved :: MIT License
Classifier: Operating System :: OS Independent
Classifier: Programming Language :: Python
Classifier: Typing :: Typed
Classifier: Topic :: Scientific/Engineering :: Bio-Informatics
Classifier: Topic :: Utilities
Requires-Dist: ncbi-genome-download
Requires-Dist: click
Project-URL: Documentation, https://avilpage.com/kdb.html
Project-URL: Source, https://github.com/avilpage/kraken-db-builder
